NLPToolkitX/__init__.py
NLPToolkitX/main.py
NLPToolkitX/slang.txt
NLPToolkitX/utils_slang.py
nlptoolkitx-0.1.1.dist-info/METADATA
nlptoolkitx-0.1.1.dist-info/WHEEL
nlptoolkitx-0.1.1.dist-info/top_level.txt
nlptoolkitx-0.1.1.dist-info/RECORD
