Metadata-Version: 2.4
Name: NLPToolkitX
Version: 0.1.1
Summary: A simple, configurable NLP preprocessing toolkit.
Author-email: Dipto Sen <diptosen2017@gmail.com>
License: MIT License
Project-URL: Homepage, https://github.com/dipto8103/NLPToolkitX
Project-URL: Repository, https://github.com/dipto8103/NLPToolkitX
Project-URL: Issue Tracker, https://github.com/dipto8103/NLPToolkitX/issues
Classifier: Development Status :: 3 - Alpha
Classifier: Intended Audience :: Science/Research
Classifier: Topic :: Scientific/Engineering :: Artificial Intelligence
Classifier: License :: OSI Approved :: MIT License
Classifier: Programming Language :: Python :: 3
Classifier: Programming Language :: Python :: 3 :: Only
Classifier: Programming Language :: Python :: 3.8
Classifier: Programming Language :: Python :: 3.9
Classifier: Programming Language :: Python :: 3.10
Classifier: Programming Language :: Python :: 3.11
Classifier: Operating System :: OS Independent
Requires-Python: >=3.7
Requires-Dist: pandas>=1.3
Requires-Dist: numpy>=1.21
Requires-Dist: tabulate>=0.8
Requires-Dist: emoji>=2.0
Requires-Dist: nltk>=3.6
Requires-Dist: contractions>=0.1.73
Provides-Extra: torch
Requires-Dist: torch>=1.8; extra == "torch"
